pdfimageextractor/extractpdfimages.py
pdfimageextractor-0.1.1.dist-info/METADATA
pdfimageextractor-0.1.1.dist-info/WHEEL
pdfimageextractor-0.1.1.dist-info/entry_points.txt
pdfimageextractor-0.1.1.dist-info/RECORD
