Metadata-Version: 2.4
Name: pdfimageextractor
Version: 0.1.1
Summary: Extract high-quality images from PDF files while preserving metadata
Project-URL: Homepage, https://github.com/nealcaren/pdfimageextractor
Project-URL: Repository, https://github.com/nealcaren/pdfimageextractor.git
Author-email: Neal Caren <neal.caren@unc.edu>
License: MIT
Keywords: extraction,images,pdf
Classifier: Development Status :: 4 - Beta
Classifier: Intended Audience :: End Users/Desktop
Classifier: License :: OSI Approved :: MIT License
Classifier: Programming Language :: Python :: 3
Classifier: Programming Language :: Python :: 3.8
Classifier: Programming Language :: Python :: 3.9
Classifier: Programming Language :: Python :: 3.10
Classifier: Topic :: Multimedia :: Graphics
Requires-Python: >=3.8
Requires-Dist: pillow
Requires-Dist: pymupdf
Provides-Extra: dev
Requires-Dist: black>=23.0; extra == 'dev'
Requires-Dist: flake8>=6.0; extra == 'dev'
Requires-Dist: isort>=5.0; extra == 'dev'
Requires-Dist: pytest-cov>=4.0; extra == 'dev'
Requires-Dist: pytest>=7.0; extra == 'dev'
